orchestral/__init__.py
orchestral/error.py
orchestral/group.py
orchestral/orchestral.py
orchestral/step.py
orchestral/step_type.py
orchestral/workflow.py
orchestral/workflow_status.py
orchestral-0.1.2.dist-info/licenses/LICENSE
orchestral-0.1.2.dist-info/METADATA
orchestral-0.1.2.dist-info/WHEEL
orchestral-0.1.2.dist-info/top_level.txt
orchestral-0.1.2.dist-info/RECORD
