Metadata-Version: 2.4
Name: orchestral
Version: 0.1.2
Summary: A library for for orchestrating tasks asynchronously.
Author-email: Ada Lundhe <adalundhe@lundhe.audio>
License: MIT License
Keywords: pypi,cicd,python,workflows,task,runner,async
Classifier: Programming Language :: Python :: 3.11
Classifier: Programming Language :: Python :: 3.12
Classifier: Programming Language :: Python :: 3.13
Classifier: License :: OSI Approved :: MIT License
Classifier: Operating System :: OS Independent
Requires-Python: >=3.11
License-File: LICENSE
Requires-Dist: taskex
Dynamic: license-file
